{
    "00:00" : "background",
    "00:09" : "heavy-kidding",
    "00:23" : "background",
    "00:30" : "heavy-kidding",
    "00:33" : "background",
    "00:53" : "heavy-kidding",
    "01:15" : "background",
    "02:31" : "heavy-kidding",
    "10:26" : "background",
    "11:10" : "heavy-kidding",
    "11:33" : "background",
    "12:17" : "heavy-kidding",
    "12:34" : "background",
    "12:38" : "heavy-kidding",
    "12:40" : "background",
    "12:47" : "heavy-kidding",
    "12:59" : "background",
    "13:24" : "heavy-kidding",
    "13:26" : "background",
    "13:33" : "heavy-kidding",
    "13:48" : "background",
    "13:53" : "heavy-kidding",
    "13:54" : "background",
    "14:00" : "heavy-kidding",
    "14:02" : "background",
    "14:22" : "heavy-kidding",
    "14:25" : "background",
    "14:32" : "heavy-kidding",
}
